LICENSE-GPL.txt
LICENSE-LGPL.txt
MANIFEST.in
README.md
setup.py
pygeo/__init__.c
pygeo/__init__.py
pygeo/analysis.c
pygeo/analysis.pyx
pygeo/analysis.pyxbld
pygeo/autopick.c
pygeo/autopick.pyx
pygeo/autopick.pyxbld
pygeo/coord.c
pygeo/coord.py
pygeo/dipfilt.c
pygeo/dipfilt.pyx
pygeo/dipfilt.pyxbld
pygeo/fastio.c
pygeo/fastio.py
pygeo/filter.c
pygeo/filter.h
pygeo/fpconvert.c
pygeo/fpconvert.h
pygeo/fullpy.c
pygeo/fullpy.py
pygeo/rsfread.c
pygeo/rsfread.py
pygeo/segyarray.c
pygeo/segyarray.py
pygeo/segyread.c
pygeo/segyread.pyx
pygeo/segyread.pyxbld
pygeo/testing.c
pygeo/testing.py
pygeo.egg-info/PKG-INFO
pygeo.egg-info/SOURCES.txt
pygeo.egg-info/dependency_links.txt
pygeo.egg-info/pbr.json
pygeo.egg-info/requires.txt
pygeo.egg-info/top_level.txt
pygeo/clfiles/__init__.py
pygeo/clfiles/filter.cl