Metadata-Version: 1.1
Name: pygeo
Version: 0.1.3
Summary: pygeo
Home-page: https://github.com/bsmithyman/pygeo
Author: Brendan Smithyman
Author-email: brendan@bitsmithy.net
License: LGPL
Download-URL: https://github.com/bsmithyman/pygeo
Keywords: exploration seismology geophysics
Platform: Linux
Platform: Solaris
Platform: Mac OS-X
Platform: Unix
Classifier: Development Status :: 4 - Beta
Classifier: Intended Audience :: Developers
Classifier: Intended Audience :: Science/Research
Classifier: License :: OSI Approved :: GNU Lesser General Public License v3 (LGPLv3)
Classifier: Programming Language :: Python
Classifier: Topic :: Scientific/Engineering
Classifier: Topic :: Scientific/Engineering :: Mathematics
Classifier: Topic :: Scientific/Engineering :: Physics
Classifier: Operating System :: Microsoft :: Windows
Classifier: Operating System :: POSIX
Classifier: Operating System :: Unix
Classifier: Operating System :: MacOS
Classifier: Natural Language :: English
